Workbook

Sheet Cover
A1: MoH D6 & D7 Proactive Validator Checklist
A2: Working instrument for the ITU Project Manager — extended beyond the original 50-item participant checklist
A4: Programme | B4: Progressa Enterprise Architecture Programme — [contract reference]
A5: Audience | B5: ITU Project Manager (validator), ITU Analyst (scribe), MoH Review Coordinator
A6: Purpose | B6: Force active verification of each validation statement — probes, evidence, red flags — instead of passive ‘confirm’
A7: Companion | B7: MoH D6 & D7 Validation Checklist.pdf (50 items); MoH_D6_D7_Validation_Session.pptx (23 slides); 3-Day Agenda v1.1 (PM-led)
A8: Version | B8: v1.0 — 19 April 2026
A10: How to use this workbook
A12: 1. | B12: Work through tabs in order. V0 before Day 1; P on Day 1 morning; B/D/A/I/T/R1/R2/R3/R4 during sessions; G/L in parallel with Day 1–3; K in Day 3 morning; X between sessions; S and PR at session close-outs.
A13: 2. | B13: For each core item: read the Statement to the room; ask BOTH probes; wait for substantive answers; record Evidence. Only mark Confirmed OK if evidence is present AND no red-flag pattern was uttered.
A14: 3. | B14: If a Red-flag pattern is heard, do NOT mark Confirmed. Classify instead as Clarification / Correction / Objection / Enhancement per the rules.
A15: 4. | B15: Any deep-technical question beyond the PM brief is PARKED verbatim and deferred to the Lead Architect for written response within 48 hours of Day 3 close.
A16: 5. | B16: Linked items: if you classify an item, check every item listed in Linked — there is likely a propagation effect.
A17: 6. | B17: At end of each day: run Tab 16 (Process Integrity) self-check before leaving the room. At end of Day 3: Tab 17 (Dashboard) must show zero Pending before the decision memo is signed.
A20: Classification legend
A22: Category | B22: Meaning | C22: Priority
A23: Confirmed OK | B23: Statement is accepted with evidence; no red-flag pattern. | C23: NONE
A24: Correction | B24: A factual error that must be fixed. | C24: HIGH
A25: Clarification | B25: Unclear or insufficiently evidenced; needs more info before Confirm. | C25: MEDIUM
A26: Enhancement | B26: A suggestion to improve; not blocking. | C26: LOW
A27: Objection | B27: Fundamental disagreement; cannot proceed without resolution. | C27: CRITICAL
A28: N/A | B28: Item does not apply to this workshop / stakeholder. | C28: NONE
A29: Pending | B29: Not yet reviewed. | C29: NONE

Sheet V0 Pre-workshop
A1: V0 — Pre-workshop Readiness (run BEFORE Day 1)
A3: ID | B3: Check / Statement | C3: How to Verify (Procedure / Probe) | D3: Evidence Required | E3: Red-flag Pattern | F3: Owner | G3: Status | H3: Notes
A4: V01 | B4: Participant list is complete; every mandatory attendee has accepted. | C4: Review RSVP tracker; for each mandatory role cross-check acceptance. | D4: Signed attendance commitment per mandatory role. | E4: Any unreturned mandatory RSVP → escalate to PS chief of staff. | F4: ITU Analyst | G4: Pending
A5: V02 | B5: All participants received digital pack (D6, D7, checklist) by T-10. | C5: Send tracker; re-send to non-openers. | D5: E-mail receipts; read-receipt log (where available). | E5: ≥30% of participants didn’t open by T-5 → PM calls them directly. | F5: ITU Analyst | G5: Pending
A6: V03 | B6: Printed bundles delivered to each attendee by T-5. | C6: Physical stock count; delivery confirmation. | D6: Courier / MoH logistics sign-off. | E6: Less than one bundle per seat → Blocked. | F6: MoH logistics | G6: Pending
A7: V04 | B7: PS delegation pre-read briefing completed (T-7). | C7: Calendar shows 60-min slot; briefing pack delivered. | D7: Briefing deck; PS office confirmation. | E7: PS delegation didn’t attend → reschedule pre-read. | F7: ITU Project Manager | G7: Pending
A8: V05 | B8: Each programme lead walk-through completed (T-3). | C8: 8 walk-throughs done; notes captured. | D8: Walk-through notes per programme lead. | E8: Missed walk-through → cover with live briefing Day 1 morning. | F8: ITU Project Manager | G8: Pending
A9: V06 | B9: Decision signatories (PS, PDGA DG, RDIP PM) confirmed attendance for entire Day 3. | C9: Calendar holds in all three diaries. | D9: Dual-confirmed calendar invitations. | E9: Any partial attendance → decision-memo plan B. | F9: PS Chief of Staff | G9: Pending
A10: V07 | B10: Venue booked, tested (projector, network, breakout). | C10: Walk the room T-1; test projector; test network speed. | D10: Test report; contingency laptop + HDMI adapter. | E10: Network < 10 Mbps → print-only fallback prepared. | F10: ITU Analyst + MoH logistics | G10: Pending
A11: V08 | B11: Feedback log spreadsheet prepared and tested; real-time editing works. | C11: Dry-run populate 3 test items. | D11: Test-populated feedback log. | E11: Cloud-sync flaky → use local + manual sync. | F11: ITU Analyst | G11: Pending
A12: V09 | B12: Parking-lot flipchart and coloured-dot stickers available. | C12: Physical inventory in the room. | D12: Photo of set-up. | E12: Missing → procure day-before. | F12: ITU Analyst | G12: Pending
A13: V10 | B13: Category posters (CORRECTION / CLARIFICATION / ENHANCEMENT / OBJECTION) printed and mounted. | C13: Wall-mount in sight of every participant. | D13: Photo of posters. | E13: Missing → print on A3. | F13: ITU Analyst | G13: Pending
A14: V11 | B14: PM T-8 hand-over from Lead Architect complete; hotspot list in hand. | C14: Half-day session completed; PM briefing pack received. | D14: Hand-over meeting notes; hotspot list. | E14: Any slide the PM cannot explain in their own words → extra coaching. | F14: ITU PM + Lead Architect | G14: Pending
A15: V12 | B15: PM has scripted responses for the top-5 likely objections. | C15: Review objection playbook; PM rehearsal. | D15: Scripted responses document. | E15: PM hasn’t rehearsed → last-day rehearsal mandatory. | F15: ITU Project Manager | G15: Pending
... A18: V15 | B18: Emergency technical contact (Lead Architect) reachable within 48h. | C18: Architect’s phone/e-mail distributed to PM team. | D18: Contact sheet. | E18: Unreachable — backup contact named. | F18: ITU Project Manager | G18: Pending

Sheet P Premise
A1: P — D5 Premise Re-confirmation (Day 1 morning, S1.2)
A3: ID | B3: Check / Statement | C3: How to Verify (Procedure / Probe) | D3: Evidence Required | E3: Red-flag Pattern | F3: Owner | G3: Status | H3: Notes
A4: P01 | B4: ~90 health facilities figure accepted by MoH delegation. | C4: Facilitator reads figure; pause for objection. | D4: No floor objection. | E4: Any objection → Correction; escalate to D5 re-open decision. | F4: Director of Health Services | G4: Pending
A5: P02 | B5: 2–3M population served figure accepted. | C5: Facilitator reads; pause for objection. | D5: No objection. | E5: Objection on population → Correction. | F5: MoH PS | G5: Pending
A6: P03 | B6: Eight digital systems list is complete (no missing system). | C6: Read list: DHIS2, eCRVS/CIVIS, e-NHIS, SPT, A-LIS, OpenLMIS pilot, SMS for Health, Stock-out module(?). | D6: Programme leads confirm no omission. | E6: Any programme lead names a missing system → Correction. | F6: DHDD Director + programme leads | G6: Pending
A7: P04 | B7: The single automated integration (SPT-to-DHIS2) is accurate. | C7: Facilitator reads; ask if any other automation exists. | D7: No missing automation. | E7: Someone names another automation → Correction to D5 and cascades. | F7: HMIS Coordinator | G7: Pending
A8: P05 | B8: ~90% paper-clinical-records figure accepted. | C8: Read figure; pause. | D8: No objection. | E8: Objection → Clarification. | F8: Director of Health Services | G8: Pending
A9: P06 | B9: ~50% eCRVS population coverage accepted. | C9: Read figure; eCRVS lead confirms. | D9: eCRVS confirmation. | E9: eCRVS lead disputes → Correction. | F9: eCRVS/CIVIS lead | G9: Pending
A10: P07 | B10: ~30% e-NHIS enrolment (vs 60k target) accepted. | C10: Read figure; NHIA confirms. | D10: NHIA confirmation. | E10: NHIA disputes → Correction. | F10: e-NHIS CEO | G10: Pending
A11: P08 | B11: ~60% national electricity access accepted as baseline for offline-first design. | C11: Read; accept as baseline. | D11: No objection. | E11: Any dispute → Clarification; offline-first principle unchanged. | F11: PDGA DG | G11: Pending

Sheet B Business
A1: Core Validation — Business Architecture (D6 §3)
A3: ID | B3: D6/D7 Ref | C3: Statement | D3: Probe 1 | E3: Probe 2 | F3: Evidence Required | G3: Red-flag Answers | H3: Primary Response Owner | I3: Linked Items | J3: Classification | K3: Verbatim Comment | L3: Proposed Change | M3: Action Owner | N3: Deadline
A4: B01 | B4: D6 §3.1.1 | C4: The three-tier governance structure (NDHSC → DHDD → 3 TWGs) is appropriate for MoH and addresses the current coordination gap across digital health systems. | D4: Who chairs NDHSC, and has the Permanent Secretary explicitly confirmed the chair role? | E4: By which quarter can the Ministerial Order establishing NDHSC realistically be signed? | F4: PS verbal confirmation on record; target quarter for Ministerial Order; Financial Regulations reference for the authority threshold. | G4: “We'd need cabinet consultation” / “Threshold should change” / PS silent → do NOT mark Confirmed. | H4: MoH Permanent Secretary | I4: G04, L02, R102 | J4: Pending
A5: B02 | B5: D6 §3.1.1 | C5: NDHSC composition (14 members, PS chair, quarterly meetings, authority over investments > USD 50,000) is correct and workable. | D5: Do all 14 roles currently exist and have incumbents, or are any vacant / under reorganisation? | E5: Is the quarterly cadence compatible with the PS calendar, and should observer seats exist for PDGA / RDIP / WHO? | F5: Role list with incumbent names; calendar pre-commitment; observer-seat decision. | G5: Role doesn’t exist / cadence rejected / threshold disputed. | H5: MoH Permanent Secretary + DHDD Director | I5: B01 | J5: Pending
A6: B03 | B6: D6 §3.1.2 | C6: Upgrading the HMIS team to the Digital Health and Data Directorate (DHDD), with 14 positions across 6 functional areas phased 2025–2028, is realistic within MoH administrative constraints. | D6: Under which civil-service grades do the 14 positions fall, and does the PSC recruitment calendar allow the phased schedule? | E6: Are the proposed salaries competitive against the Progressa ICT market, and what secondment or RDIP top-up is planned if not? | F6: Civil-service grading letter; PSC recruitment calendar commitment; salary benchmark; RDIP supplementation plan. | G6: “The grades don’t exist” / “The salaries are uncompetitive” → Correction. | H6: MoH PS + DHDD Director + PSC liaison | I6: K04, G09 | J6: Pending
A7: B04 | B7: D6 §3.2 | C7: The capability maturity targets (Level 3–4 by 2033 for core health-information capabilities) are ambitious but achievable given the investment and timeframes proposed. | D7: Against which maturity-model definition are the levels measured (HIMSS / OpenHIE / custom)? | E7: If Wave 1 delivery slips by 6 months, which targets most at risk and does the roadmap admit that? | F7: Named maturity-model reference; sensitivity analysis in roadmap. | G7: “We need to see the maturity rubric” → Clarification. | H7: DHDD Director | I7: R105 | J7: Pending
A8: B05 | B8: D6 §3.3 | C8: The eight priority business processes selected for digitisation correctly reflect MoH’s priorities. | D8: Is there a process missing from the list (e.g. human-resources-for-health; referrals; emergency dispatch)? | E8: Is any process on the list out-of-scope or not a priority (e.g. is drug supply a pharmacy function rather than MoH)? | F8: Written endorsement from each programme lead present. | G8: Programme lead says “the real priority is X” → Correction. | H8: Director of Health Services + 8 programme leads | I8: X01 | J8: Pending
A9: B06 | B9: D6 §3.3.2 | C9: The clinical workflow and service-delivery impacts described for each process accurately reflect how health workers currently operate and what they will need in the future. | D9: Has a facility-based clinician actually reviewed the workflow descriptions? If yes, who? | E9: What is the biggest workflow friction likely when moving from paper to digital at a busy HC? | F9: Named clinician reviewer; top-3 friction list. | G9: “No clinician has reviewed this” → Clarification + escalate to rapid clinician review. | H9: Director of Health Services | I9: K09 | J9: Pending
A10: B07 | B10: D6 §3.4 | C10: The e-NHIS enrolment expansion from 15,000–20,000 to 60,000+ beneficiaries via mobile enrolment and eCRVS-NIN integration is feasible. | D10: Does NHIA have call-centre, agent-network and premises capacity for a ~4× enrolment step? | E10: Is the eCRVS API actually ready for real-time eligibility lookup, or is this assumed? | F10: NHIA board endorsement letter; eCRVS API readiness attestation; operational-capacity plan. | G10: “We assume the API will be ready” → Clarification (must be verified). | H10: e-NHIS/NHIA CEO | I10: G02, G06 | J10: Pending

Sheet D Data
A1: Core Validation — Data Architecture (D6 §4)
A3: ID | B3: D6/D7 Ref | C3: Statement | D3: Probe 1 | E3: Probe 2 | F3: Evidence Required | G3: Red-flag Answers | H3: Primary Response Owner | I3: Linked Items | J3: Classification | K3: Verbatim Comment | L3: Proposed Change | M3: Action Owner | N3: Deadline
A4: D01 | B4: D6 §4.1 | C4: The data governance framework (11 domains, Director-level Data Owners, four-tier classification, formal data-sharing agreements) is appropriate for MoH. | D4: For each of the 11 domains, who is the proposed named Data Owner? | E4: Is there a data-sharing MoU template ready, and has DPO reviewed it? | F4: 11-domain Data-Owner list; MoU template; DPO review memo. | G4: “Owners to be named later” → Clarification; cannot Confirm. | H4: DHDD Director + Data Protection Office | I4: G10, L06 | J4: Pending
A5: D02 | B5: D6 §4.2.1 | C5: The MPI strategy (eCRVS NIN as primary identifier, managed through OpenCR with probabilistic matching) is the correct patient-identity approach. | D5: What false-positive / false-negative thresholds are acceptable for probabilistic matching? | E5: For patients without a NIN, what is the enrolment path and who issues a temporary identifier? | F5: Matching threshold policy; unmatched-patient SOP. | G5: “We’ll figure out the thresholds” → Clarification. | H5: DHDD Director + eCRVS/CIVIS lead | I5: G02, G03, A03 | J5: Pending
A6: D03 | B6: D6 §4.2.1 | C6: The data flows between DHIS2, eCRVS, e-NHIS, OpenMRS and A-LIS are accurately and completely described. | D6: Is any major flow missing (e.g. pharmacy, lab-to-clinician)? | E6: Are the described flows validated by the owning system’s technical lead? | F6: Confirmation from each system technical lead; missing-flow list. | G6: System owner doesn’t recognise the flow as described → Correction. | H6: DHDD Director | I6: I02 | J6: Pending
A7: D04 | B7: D6 §4.2.4 | C7: Phased standards adoption (ICD-11 and LOINC first, then SNOMED CT GPS and ATC) is correctly sequenced for MoH’s context and current capacity. | D7: Is local clinical-coding capacity sufficient for ICD-11 in Wave 1, or is training required? | E7: What is the source authority for LOINC code selection (local panel, WHO, reference lab)? | F7: Training plan for coders; LOINC authority source. | G7: “Coders aren’t trained” → Clarification; escalate. | H7: HMIS Coordinator + Lab lead | I7: A07 | J7: Pending
A8: D05 | B8: D6 §4.4 | C8: The role of DHIS2 as national health-analytics platform, with a Wave 3 health-data warehouse, is appropriate. | D8: If an urgent cross-domain analytic need arises in Wave 2, what is the stop-gap? | E8: Who will run the Wave-3 warehouse — DHDD or a separate analytics unit? | F8: Stop-gap plan (e.g. DHIS2 pivot, Superset); governance for the warehouse. | G8: “We’ll deal with Wave-2 analytics when we get there” → Clarification. | H8: DHDD Director | I8: R104 | J8: Pending
A9: D06 | B9: D6 §4.5 | C9: The data-residency requirement — all identifiable health data hosted on sovereign (nationally controlled) infrastructure — is correct in the absence of a national data-protection law. | D9: Does ProgTel/e-Gov DC legally qualify as ‘sovereign’ for the interim? | E9: What happens to PII in the interim period before G-Cloud? | F9: Sovereignty legal opinion; interim PII-handling SOP. | G9: “We’ll clarify sovereignty later” → Objection risk. | H9: PDGA DG + Data Protection Office | I9: L01, L06, T01 | J9: Pending

Sheet A Application
A1: Core Validation — Application Architecture (D6 §5)
A3: ID | B3: D6/D7 Ref | C3: Statement | D3: Probe 1 | E3: Probe 2 | F3: Evidence Required | G3: Red-flag Answers | H3: Primary Response Owner | I3: Linked Items | J3: Classification | K3: Verbatim Comment | L3: Proposed Change | M3: Action Owner | N3: Deadline
A4: A01 | B4: D6 §5.2.1 | C4: DHIS2’s role as the strengthened national HMIS and analytics platform, with Tracker expanded for EIR and case-based IDSR, is correctly described. | D4: Is the DHIS2 instance version current and supported, or does it need an upgrade? | E4: Who will perform Tracker configuration for EIR and IDSR, and under what SLA? | F4: DHIS2 version/support status; Tracker config provider (HISP regional node / MoH). | G4: “The instance is out of support” → Correction. | H4: HMIS Coordinator + HISP regional node | I4: G08, A05, A08 | J4: Pending
A5: A02 | B5: D6 §5.2.2 | C5: OpenHIM as the HIE mediator — the hub through which all systems connect — is the correct platform. | D5: Who will run OpenHIM in production after Wave 1? | E5: Is the required OpenHIM operational skillset inside DHDD, or must it be contracted in? | F5: Operational owner; skills inventory + contract plan. | G5: “We’ll find someone” → Clarification. | H5: DHDD Director | I5: B03, I01 | J5: Pending
A6: A03 | B6: D6 §5.2.3 | C6: OpenCR as the MPI platform, anchored to eCRVS NIN, is the correct choice. | D6: What migration approach is planned for the ~1M eCRVS records becoming the MPI seed? | E6: Does OpenCR deployment require a separate infrastructure spec, or does it co-host with OpenHIM? | F6: MPI seed migration plan; OpenCR infra spec. | G6: “The migration is a detail” → Clarification. | H6: DHDD Director + eCRVS/CIVIS lead | I6: D02, G02 | J6: Pending
A7: A04 | B7: D6 §5.3.1 | C7: OpenMRS as the preferred EHR, deployed first at 15–20 facilities (maternal + HIV/ART) and expanding to 30–40 by 2033, is the right approach. | D7: Have the 15–20 pilot facilities been named, and do the facility managers know? | E7: Is OpenMRS to be deployed vanilla, or are local customisations planned? Who owns them? | F7: Named facility list; customisation plan + owner. | G7: “Facilities to be selected later” → Clarification. | H7: Director of Health Services + MCH / HIV programme leads | I7: B06, K09 | J7: Pending
A8: A05 | B8: D6 §5.3.2 | C8: The phased SPT → DHIS2 Tracker EIR transition over 3–5 years — maintaining SPT until Tracker proves ≥95% equivalence — is correctly planned and appropriately cautious. | D8: How is ≥95% equivalence measured, and over what sample size / duration? | E8: Who owns the measurement, and what is the arbitration path if SPT and Tracker disagree? | F8: Equivalence measurement protocol; arbitrator named. | G8: “We’ll work it out operationally” → Clarification. | H8: EPI programme lead + HMIS coordinator | I8: A01 | J8: Pending
A9: A06 | B9: D6 §5.4.1 | C9: e-NHIS enhancement (mobile enrolment via USSD/app, offline claims following CLAIM-it, eCRVS-NIN integration) — rather than replacement — is the right decision. | D9: Has the NHIA board formally endorsed enhancement over replacement? | E9: Is the CLAIM-it pattern a fit for the current e-NHIS codebase, or does it require forking? | F9: Board endorsement memo; technical fit assessment. | G9: Board hasn’t considered → Clarification + escalate. | H9: NHIA CEO/COO | I9: B07, G06 | J9: Pending
A10: A07 | B10: D6 §5.3.3 | C10: A-LIS strengthening (LOINC coding for 50–80 priority tests, FHIR DiagnosticReport interface, scale to reference and regional labs) is feasible and appropriate. | D10: Is the 50–80 test panel agreed by the National Public Health Lab? | E10: Which labs beyond NPHL will be in scope by Wave 2, and do they have the equipment/skills? | F10: Agreed test panel; lab-expansion list with readiness status. | G10: Panel not agreed → Correction. | H10: National Public Health Lab + Lab lead | I10: D04 | J10: Pending
A11: A08 | B11: D6 §5.5 | C11: Disease-surveillance modernisation (DHIS2 Tracker for case-based IDSR starting with 7 priority notifiable conditions) is correct and builds on existing DHIS2 investment. | D11: Are the 7 priority notifiable conditions confirmed by the IDSR programme and WHO? | E11: What reporting cadence is expected, and is it compatible with facility workloads? | F11: Condition list endorsed; cadence statement. | G11: Condition list disputed → Correction. | H11: IDSR programme lead + WHO | I11: G07, A01 | J11: Pending

Sheet I Integration
A1: Core Validation — Integration Architecture (D6 §6)
A3: ID | B3: D6/D7 Ref | C3: Statement | D3: Probe 1 | E3: Probe 2 | F3: Evidence Required | G3: Red-flag Answers | H3: Primary Response Owner | I3: Linked Items | J3: Classification | K3: Verbatim Comment | L3: Proposed Change | M3: Action Owner | N3: Deadline
A4: I01 | B4: D6 §6.1.2 | C4: The hub-and-spoke integration model (all systems through OpenHIM rather than direct peer connections) is the correct architectural approach. | D4: Are there any existing point-to-point integrations that would be demoted to OpenHIM, and over what timeline? | E4: If OpenHIM is unavailable, is any critical flow blocked, and what is the DR strategy? | F4: Point-to-point decommissioning list; DR plan for OpenHIM. | G4: “DR to be designed later” → Clarification. | H4: DHDD Director | I4: A02, T11 | J4: Pending
A5: I02 | B5: D6 §6.2 | C5: The six priority flows are correctly identified and appropriately sequenced (Flow 1 first; 3–5 in Wave 2; Flow 6 in Wave 3). | D5: Are any flows missing (e.g. pharmacy, referral, mortality)? | E5: Is the Wave-1 Flow 1 realistic given eCRVS, OpenCR, and e-NHIS co-availability? | F5: Missing-flow statement; Wave-1 Flow-1 feasibility note. | G5: “Flow 1 depends on things we don’t control” → Objection. | H5: DHDD Director | I5: A02, A03, G02 | J5: Pending
A6: I03 | B6: D6 §6.1.3 | C6: The three-phase integration maturity progression (batch → API point-to-point → HIE-mediated) is realistic and appropriately paced. | D6: What exit criteria promote a flow from one phase to the next? | E6: Are there any flows that should skip phases, and why? | F6: Phase-exit criteria table; skip-phase exceptions list. | G6: “Phase transitions are judgement calls” → Clarification. | H6: DHDD Director | I6: I02 | J6: Pending
A7: I04 | B7: D6 §6.3 | C7: The three-tier standards approach (FHIR R4 for patient data, ADX for DHIS2 aggregate, FHIR Facade adapters for legacy) is correct. | D7: Which FHIR profiles will be used (IPS, SVCM, MII, custom), and who owns them? | E7: What ADX mapping tables exist, and who maintains them? | F7: Profile owner list; ADX mapping table location. | G7: “Profiles to be defined during build” → Clarification. | H7: DHDD Director + WHO technical lead | I7: G07 | J7: Pending
A8: I05 | B8: D6 §6.2.1 | C8: The statement that SPT-to-DHIS2 is the sole currently operational automated integration accurately reflects the current state. | D8: Are there informal/undocumented automations anywhere (e.g. scheduled scripts, file drops)? | E8: Does the statement include or exclude batch-file loads? | F8: Informal-automation sweep; batch-file inclusion statement. | G8: “There’s one more but it’s half-working” → Correction. | H8: HMIS Coordinator | I8: (D5 premise) | J8: Pending

Sheet T Technology
A1: Core Validation — Technology Architecture (D6 §7)
A3: ID | B3: D6/D7 Ref | C3: Statement | D3: Probe 1 | E3: Probe 2 | F3: Evidence Required | G3: Red-flag Answers | H3: Primary Response Owner | I3: Linked Items | J3: Classification | K3: Verbatim Comment | L3: Proposed Change | M3: Action Owner | N3: Deadline
A4: T01 | B4: D6 §7.1 | C4: The dual-mode hosting strategy (interim ProgTel/e-Gov DC, target G-Cloud via RDIP by 2027) is practical and correctly designed. | D4: Has RDIP given a written commitment to the 2027 G-Cloud delivery date? | E4: What is the migration plan from interim to G-Cloud, and has it been budgeted? | F4: RDIP commitment letter; migration plan + budget line. | G4: “G-Cloud is expected” (no letter) → Objection risk. | H4: PDGA DG + RDIP PM | I4: G01, T05, D06 | J4: Pending
A5: T02 | B5: D6 §7.2.3 | C5: The offline-first mandatory design principle is correct given ~60% national electricity access. | D5: Is every Wave-1 platform choice actually offline-capable, or are some cloud-only? | E5: What endpoint device spec is mandated at facilities (tablet, laptop, solar power, UPS)? | F5: Offline-capability matrix per platform; endpoint spec. | G5: “We’ll require cloud when available” → Correction. | H5: DHDD Director + PDGA | I5: T03 | J5: Pending
A6: T03 | B6: D6 §7.2 | C6: The rural connectivity strategy (EHSSP satellite bridge, RDIP broadband target, offline-first baseline) adequately addresses facility-level gaps. | D6: Who funds the EHSSP bridge (Aug 2025+), and for how long? | E6: Which 30–50 priority facilities are on the short-list, and do they have a working power supply? | F6: Bridge-funding source letter; priority-facility list + power audit. | G6: “The gap will be closed by RDIP” (no letter) → Objection. | H6: PDGA DG + RDIP PM + MoH DHS | I6: G04, K03 | J6: Pending
A7: T04 | B7: D6 §7.4 | C7: Security architecture requirements (TLS 1.2+, AES-256, OAuth 2.0 + mTLS, MFA for admins, RBAC) are appropriate and sufficient. | D7: Is there a national cyber-security baseline MoH must align to beyond these? | E7: Who runs the MFA system — DHDD or PDGA — and what is the break-glass procedure? | F7: National cyber baseline reference; MFA operator + break-glass SOP. | G7: “MFA operations to be decided” → Clarification. | H7: PDGA DG + DHDD Director | I7: (cross-ministry) | J7: Pending
A8: T05 | B8: D6 §7.1.5 | C8: Containerised interim hosting on PDGA/ProgTel is practical for the pre-G-Cloud period. | D8: Does ProgTel/e-Gov DC have Docker/Kubernetes operator skills today? | E8: Is capacity sized for Wave-1 platform set (OpenHIM + OpenCR + DHIS2 + eLMIS)? | F8: Skills audit; capacity-sizing document. | G8: “Capacity to be sized” → Clarification. | H8: PDGA DG | I8: T01 | J8: Pending
A9: T06 | B9: D6 §7.5 | C9: The technology stack (open-source, Docker/Kubernetes, Keycloak) is appropriate and consistent with open-standards and sustainability principles. | D9: Who provides vendor-grade support for each open-source component after Wave 1? | E9: Are any proprietary components still needed, and if so under what licence model? | F9: Support-contract plan per component; proprietary-component list. | G9: “Support to be sourced” → Clarification. | H9: DHDD Director + PDGA DG | I9: K10 | J9: Pending

Sheet R1 Timeline
A1: Core Validation — D7 Roadmap Timeline (D7 §4)
A3: ID | B3: D6/D7 Ref | C3: Statement | D3: Probe 1 | E3: Probe 2 | F3: Evidence Required | G3: Red-flag Answers | H3: Primary Response Owner | I3: Linked Items | J3: Classification | K3: Verbatim Comment | L3: Proposed Change | M3: Action Owner | N3: Deadline
A4: R101 | B4: D7 §4.1 | C4: The three-wave phasing (Wave 1 2025–2026, Wave 2 2027–2029, Wave 3 2030–2033) is logical and correctly sequences governance before technology, infrastructure before applications. | D4: What is the single biggest dependency that could push Wave 1 past 2026? | E4: Is there a risk-adjusted timeline, and has it been sponsored? | F4: Top-risk named; risk-adjusted plan. | G4: “We’ll adjust as we go” → Clarification. | H4: RDIP PM + DHDD Director | I4: K03, K04, K05 | J4: Pending
A5: R102 | B5: D7 §4.2 | C5: Wave 1 priorities are correct (NDHSC/DHDD, OpenHIM + OpenCR, MPI seed, eCRVS → e-NHIS, DHIS2 Tracker pilot, eLMIS rollout, EHSSP transition). | D5: Has every Wave-1 initiative been assigned to a named implementer? | E5: Is Wave-1 Q1 2026 OpenHIM + OpenCR go-live realistic given hosting/skills gaps? | F5: Initiative-to-implementer map; Q1 2026 go-live plan. | G5: “Implementers TBA” → Clarification. | H5: DHDD Director + RDIP PM | I5: B01, A02, A03 | J5: Pending
A6: R103 | B6: D7 §4.3 | C6: Wave 2 priorities are correct (EHR at 15–20, EIR national transition, e-NHIS scaling, G-Cloud migration, full DHDD, 4–5 flows). | D6: Is the EHR pilot funded, or is it pending Wave-2 proposal? | E6: Does G-Cloud migration assume RDIP delivers 2027 on time? | F6: EHR funding status; G-Cloud-dependency flag. | G6: “Pending funding” → Clarification; link to R206. | H6: RDIP PM + DHDD Director | I6: T01, G01, R206 | J6: Pending
A7: R104 | B7: D7 §4.4 | C7: Wave 3 priorities are correct (EHR to 30–40, SPT retirement, all 6 flows at maturity, data warehouse, community surveillance, ≥50% government cost absorption). | D7: Is the ≥50% government absorption a commitment or an aspiration? | E7: What triggers Wave-3 start — a calendar date or a Wave-2 go/no-go? | F7: Commitment classification; Wave-3 start trigger. | G7: “Aspiration” → Objection-risk. | H7: MoH PS + MoF Budget | I7: R204, G09 | J7: Pending
A8: R105 | B8: D7 §4.1.5 | C8: Wave-1 → Wave-2 go/no-go criteria (DHDD ≥6 staff; OpenHIM ≥1 flow; MPI ≥500k records; DHIS2 ≥90% completeness) are appropriate and measurable. | D8: Who measures each criterion, and when in 2026? | E8: What happens if one criterion fails but others pass? | F8: Measurement owner + date; partial-pass decision rule. | G8: “Partial pass is subjective” → Clarification. | H8: DHDD Director + RDIP PM | I8: R102 | J8: Pending
A9: R106 | B9: D7 §4.6 | C9: Critical-path dependencies are correctly identified (governance → data governance → hosting → MPI → HIE → applications). | D9: Is any off-path dependency missing (e.g. endpoint devices, network, power)? | E9: If one step slips, which downstream steps are on hold vs. can proceed in parallel? | F9: Off-path dependency list; slip-propagation analysis. | G9: “We’ll rework if needed” → Clarification. | H9: RDIP PM | I9: T02, T03 | J9: Pending
A10: R107 | B10: D7 §4.2 | C10: The EHSSP W1-11 transition plan (Aug 2025 funding cliff; risk to DHIS2 reporting, SPT, e-NHIS) is an immediate priority and is adequately addressed. | D10: Has the bridge funding actually been committed by a named party (RDIP, government, donor)? | E10: What is the fallback if bridge funding isn’t secured by the cliff date? | F10: Written bridge-funding commitment; fallback plan. | G10: “We’re working on it” (with cliff < 90 days) → Objection. | H10: RDIP PM + MoH PS | I10: G04, K03 | J10: Pending

Sheet R2 Investment
A1: Core Validation — D7 Investment & Sustainability (D7 §5)
A3: ID | B3: D6/D7 Ref | C3: Statement | D3: Probe 1 | E3: Probe 2 | F3: Evidence Required | G3: Red-flag Answers | H3: Primary Response Owner | I3: Linked Items | J3: Classification | K3: Verbatim Comment | L3: Proposed Change | M3: Action Owner | N3: Deadline
A4: R201 | B4: D7 §5.2 | C4: The investment envelope USD 6.2–10.7M (midpoint 8.5M) over 8 years is realistic and proportionate. | D4: Is the range based on bottom-up wave-level costing or top-down benchmark? | E4: Does the midpoint assume all waves at target scope, or some discretion? | F4: Costing methodology statement; midpoint-assumption note. | G4: “Benchmark, refined later” → Clarification. | H4: RDIP PM + DHDD Director | I4: R206, X08 | J4: Pending
A5: R202 | B5: D7 §5.4 | C5: The funding-source mix (RDIP 22–23%, Government 18–19%, Global Fund 14–16%, GAVI 6–8%, others) is realistic and actionable. | D5: Is each donor commitment in writing, or is it mapped based on expected cycles? | E5: What is the tail risk if one major source (RDIP or Global Fund) reduces allocation? | F5: Donor commitment letters; tail-risk analysis. | G5: “Mapped, not committed” → Clarification. | H5: RDIP PM | I5: G09 | J5: Pending
A6: R203 | B6: D7 §5.5 | C6: The Wave-2 funding-gap mitigation (WB/AfDB health-digitisation proposal for USD 0.5–1M) is credible. | D6: Is a concept note already in the pipeline with a named task manager? | E6: What is the decision timeline, and does it leave time before Wave 2 starts? | F6: Concept-note status; WB/AfDB decision-calendar. | G6: “We’ll develop a concept” → Clarification. | H6: MoH PS + RDIP PM | I6: K10 | J6: Pending
A7: R204 | B7: D7 §5.6 | C7: The 6%→75% government absorption trajectory (2025–2033) is realistic. | D7: What is the concrete step to create the government digital-health budget line by 2028? | E7: Which MoF/Budget officer owns the line-creation task? | F7: Budget-line creation plan; named owner at MoF. | G7: “MoF will handle when the time comes” → Objection-risk. | H7: MoH PS + MoF Budget Dept | I7: R205, G09 | J7: Pending
A8: R205 | B8: D7 §5.7 | C8: Government establishes a digital-health budget line by 2028 — acceptable as a commitment from the MoH delegation. | D8: Is this in a signed government commitment letter for RDIP? | E8: What is the escalation path if 2028 slips? | F8: Signed commitment; escalation path. | G8: “Not yet signed” → Clarification; escalate. | H8: MoH PS | I8: R204 | J8: Pending

Sheet R3 Risks
A1: Core Validation — D7 Risk Register (D7 §6)
A3: ID | B3: D6/D7 Ref | C3: Statement | D3: Probe 1 | E3: Probe 2 | F3: Evidence Required | G3: Red-flag Answers | H3: Primary Response Owner | I3: Linked Items | J3: Classification | K3: Verbatim Comment | L3: Proposed Change | M3: Action Owner | N3: Deadline
A4: R301 | B4: D7 §6 | C4: The two Critical risks (EHSSP funding cliff; DHDD recruitment failure) are correctly flagged as Critical. | D4: Are there any currently High risks that, under present evidence, should be upgraded to Critical? | E4: Has anything happened since the draft that downgrades a Critical risk? | F4: Risk-severity re-validation memo. | G4: “The list is a snapshot” → Clarification. | H4: DHDD Director | I4: K01, K03, K04 | J4: Pending
A5: R302 | B5: D7 §6 | C5: The 10 High risks are complete and none are missing (RDIP delay, eCRVS API, NIN production, DPA, EHR adoption, budget-line, ...). | D5: Is clinician burnout in Wave-2 EHR rollout on the High list? | E5: Is vendor lock-in (OpenMRS, OpenHIM) on the list? | F5: Completeness review; missing-risks addition. | G5: Omission acknowledged → Correction. | H5: DHDD Director | I5: K02, K09 | J5: Pending
A6: R303 | B6: D7 §6 | C6: Each risk has a concrete, dated mitigation owner (not just a role). | D6: Is there any risk whose mitigation owner is ‘TBD’ or just a role name? | E6: Is there any risk whose mitigation is financial but has no budget line? | F6: Fully-populated risk register; unfunded-mitigation list. | G6: Any ‘TBD’ owner → Correction. | H6: DHDD Director | I6: K01, K02 | J6: Pending

Sheet R4 Governance
A1: Core Validation — D7 Governance, OKR, OCM, Sustainability (D7 §7)
A3: ID | B3: D6/D7 Ref | C3: Statement | D3: Probe 1 | E3: Probe 2 | F3: Evidence Required | G3: Red-flag Answers | H3: Primary Response Owner | I3: Linked Items | J3: Classification | K3: Verbatim Comment | L3: Proposed Change | M3: Action Owner | N3: Deadline
A4: R401 | B4: D7 §7 | C4: The portfolio-governance structure (NDHSC + DHDD + 3 TWGs + PMO) has clear decision rights and escalation. | D4: Which decisions are at NDHSC, which at TWG, which at DHDD, and where is the escalation path? | E4: Does RDIP PMU sit inside or outside MoH governance? | F4: Decision-rights table; RDIP positioning note. | G4: “Decision rights to be clarified” → Clarification. | H4: MoH PS + DHDD Director + RDIP PM | I4: B01 | J4: Pending
A5: R402 | B5: D7 §7 | C5: The KPI/OKR cascade (portfolio → initiative → operational) is complete. | D5: Is there a KPI for every Wave-1 initiative? | E5: Is the KPI measurable from an existing data source? | F5: Initiative-to-KPI map; data-source readiness. | G5: “KPI measurement TBD” → Clarification. | H5: DHDD Director | I5: B04, R105 | J5: Pending
A6: R403 | B6: D7 §7 | C6: The organisational-change-management plan is adequate for the clinician-facing rollouts (EHR, EIR, IDSR). | D6: Who is the named OCM lead, and what is their experience? | E6: Is there a change-champion network at facility level? | F6: OCM lead; champion network plan. | G6: “OCM is an activity, not a role” → Correction. | H6: Director of Health Services | I6: K09, B06 | J6: Pending
A7: R404 | B7: D7 §7 | C7: The sustainability financial model is credible (steady-state USD 385–515k/yr, 75% government by 2033). | D7: Is the steady-state figure inclusive of support contracts and hosting? | E7: What is the assumed inflation/FX scenario? | F7: Cost breakdown; inflation/FX assumptions. | G7: “Figures are nominal 2025 USD” → Clarification if unstated. | H7: RDIP PM + DHDD Director | I7: R204, R205 | J7: Pending
A8: R405 | B8: D7 §7 | C8: A disciplined review cadence (annual plan refresh, quarterly portfolio review, monthly TWG) is specified. | D8: Are calendar commitments already in PS and DG diaries? | E8: Who chairs each cadence, and what is the quorum? | F8: Calendar commitments; chair + quorum rules. | G8: “Cadence to be set” → Clarification. | H8: MoH PS + DHDD Director | I8: B01 | J8: Pending

Sheet G Commitments
A1: G — External-Party Commitments (RDIP / eCRVS / NHIA / WHO / HISP / MoF / DPO)
A3: ID | B3: Check / Statement | C3: How to Verify (Procedure / Probe) | D3: Evidence Required | E3: Red-flag Pattern | F3: Owner | G3: Status | H3: Notes
A4: G01 | B4: RDIP G-Cloud delivery date formally confirmed (target 2027). | C4: RDIP PM written letter referencing dates. | D4: Commitment letter with board sign-off. | E4: Verbal only → Objection-risk. | F4: RDIP PM | G4: Pending
A5: G02 | B5: eCRVS API readiness for MPI integration confirmed by eCRVS owner. | C5: API spec + readiness date from eCRVS technical owner. | D5: API readiness letter. | E5: “API is planned” → Clarification. | F5: eCRVS/CIVIS lead | G5: Pending
A6: G03 | B6: NIN production resumption timeline confirmed. | C6: Government statement on NIN programme. | D6: Official communiqué. | E6: Verbal only → Clarification. | F6: Ministry of Interior liaison | G6: Pending
A7: G04 | B7: EHSSP bridge funding source confirmed (who pays post-Aug 2025). | C7: Named payer (RDIP, government, donor) in writing. | D7: Funding letter. | E7: No named source → Objection; escalate. | F7: RDIP PM + MoH PS | G7: Pending
A8: G05 | B8: PDGA hosting commitment for interim (ProgTel/e-Gov DC) signed. | C8: PDGA hosting agreement. | D8: Signed hosting agreement with SLA. | E8: “PDGA will host” verbal → Clarification. | F8: PDGA DG | G8: Pending
A9: G06 | B9: NHIA board endorsement of e-NHIS enhancement plan. | C9: NHIA board resolution. | D9: Board minute or resolution letter. | E9: “CEO aware” → Clarification. | F9: NHIA Board / CEO | G9: Pending
A10: G07 | B10: WHO Country Office technical endorsement of surveillance and standards plan. | C10: WHO CR letter. | D10: WHO-CO endorsement letter. | E10: “WHO is supportive” → Clarification. | F10: WHO CR | G10: Pending
A11: G08 | B11: HISP regional node technical endorsement (for DHIS2 Tracker work). | C11: HISP regional node letter. | D11: HISP regional node endorsement. | E11: “HISP will help” verbal → Clarification. | F11: HISP regional node regional lead | G11: Pending
A12: G09 | B12: MoF Budget Dept endorsement of the investment envelope and budget-line path. | C12: MoF letter or minute. | D12: MoF commitment letter. | E12: “MoF will consider” → Objection-risk. | F12: MoF Budget Dept | G12: Pending
A13: G10 | B13: Data Protection Office concurrence on residency and classification in absence of DPA. | C13: DPO concurrence letter. | D13: DPO memo. | E13: “DPO consulted” → Clarification. | F13: Data Protection Office | G13: Pending

Sheet L Legal
A1: L — Legal & Regulatory Prerequisites
A3: ID | B3: Check / Statement | C3: How to Verify (Procedure / Probe) | D3: Evidence Required | E3: Red-flag Pattern | F3: Owner | G3: Status | H3: Notes
A4: L01 | B4: Data Protection Act legislative status and expected enactment date. | C4: Check legislative tracker; named Bill number and stage. | D4: Parliament tracker entry. | E4: “Coming soon” (no Bill) → Clarification. | F4: Data Protection Office | G4: Pending
A5: L02 | B5: Ministerial Order for NDHSC drafted, cabinet-cleared, signable date confirmed. | C5: Drafting status + cabinet schedule. | D5: Draft Order + cabinet agenda. | E5: Not drafted → Correction + escalate. | F5: MoH PS + Cabinet Secretariat | G5: Pending
A6: L03 | B6: Civil Service regulations re DHDD positions (grading, salaries) compatible with 14-position structure. | C6: PSC grading letter. | D6: PSC letter with grades. | E6: “Grades TBD” → Clarification. | F6: PSC + MoH HR | G6: Pending
A7: L04 | B7: Procurement regulations re open-source software deployment compatible with the stack. | C7: Procurement policy review. | D7: Procurement-policy memo. | E7: “Unusual” flags → Clarification. | F7: MoH Procurement + PDGA | G7: Pending
A8: L05 | B8: Cross-border data transfer (WHO / RHO ADX reporting) legality before DPA is in force. | C8: Legal opinion. | D8: Legal opinion memo. | E8: No legal opinion → Objection-risk. | F8: Data Protection Office + WHO | G8: Pending
A9: L06 | B9: Clinical data governance legal basis in absence of DPA (interim instrument). | C9: Ministerial Order or SI. | D9: Interim instrument draft. | E9: No interim instrument → Correction. | F9: MoH PS + DPO | G9: Pending

Sheet X Cross-ref
A1: X — Cross-Reference Integrity (PM runs these between sessions)
A3: ID | B3: Check / Statement | C3: How to Verify (Procedure / Probe) | D3: Evidence Required | E3: Red-flag Pattern | F3: Owner | G3: Status | H3: Notes
A4: X01 | B4: Every D6 §3.3 priority process has a corresponding D7 initiative in at least one wave. | C4: Cross-map 8 processes to W1–W3 initiatives. | D4: Process↔initiative map. | E4: Any orphan process → Correction. | F4: ITU PM | G4: Pending
A5: X02 | B5: Every D6 §5 system disposition maps to a D7 initiative with delivery owner. | C5: Cross-map 8 systems × disposition to initiative cards. | D5: System↔initiative map. | E5: Disposition stated but no initiative → Correction. | F5: ITU PM | G5: Pending
A6: X03 | B6: Every D6 §6 integration flow has a D7 Wave placement and an owning initiative. | C6: Cross-map 6 flows to waves. | D6: Flow↔wave map. | E6: Flow without wave → Correction. | F6: ITU PM | G6: Pending
A7: X04 | B7: D6 §7 technology choices align with D7 Wave-1 milestones (OpenHIM, OpenCR deployed on interim hosting). | C7: Cross-read §7 vs Wave-1 roadmap. | D7: Alignment note. | E7: Misalignment → Correction. | F7: ITU PM | G7: Pending
A8: X05 | B8: D6 capability targets (§3.2 Level 3–4 by 2033) align with D7 investment domain mix (Applications 43%, etc.). | C8: Check: high-maturity capability has proportional investment. | D8: Capability/investment cross-check. | E8: Mismatch → Clarification. | F8: ITU PM | G8: Pending
A9: X06 | B9: D7 go/no-go criteria reference D6 definitions (MPI 500k ↔ §4.2.1; DHIS2 90% ↔ §4.4). | C9: Trace each criterion back to D6. | D9: Trace table. | E9: Un-traceable criterion → Correction. | F9: ITU PM | G9: Pending
A10: X07 | B10: Risk register (D7 §6) references specific D6 architectural dependencies. | C10: Check each risk has D6 §-reference. | D10: Cross-ref list. | E10: Risk without D6 anchor → Correction. | F10: ITU PM | G10: Pending
A11: X08 | B11: Investment figures reconcile: D7 §5 total = sum of wave totals. | C11: Spreadsheet sum check. | D11: Arithmetic check sheet. | E11: Non-reconciling → Correction. | F11: ITU PM | G11: Pending
A12: X09 | B12: Wave 1 USD 1.8–3.0M aligns with sum of Wave-1 initiative-card costs. | C12: Sum initiative-card Wave-1 lines. | D12: Wave-1 cost check. | E12: Out of band → Correction. | F12: ITU PM | G12: Pending
A13: X10 | B13: Terminology consistency: ‘HIE’ = OpenHIM throughout; ‘MPI’ = OpenCR throughout; ‘EHR’ = OpenMRS throughout. | C13: grep across D6 and D7. | D13: Consistency report. | E13: Any alias confusion → Correction. | F13: ITU Analyst | G13: Pending

Sheet K Risks
A1: K — Risk-Register Validation (Day 3 morning)
A3: ID | B3: Check / Statement | C3: How to Verify (Procedure / Probe) | D3: Evidence Required | E3: Red-flag Pattern | F3: Owner | G3: Status | H3: Notes
A4: K01 | B4: Each of the 2 Critical risks has a NAMED individual owner (not a role). | C4: Open risk register; check owner-column content. | D4: Register with named owners. | E4: Role-only owner → Correction. | F4: DHDD Director | G4: Pending
A5: K02 | B5: Each of the 10 High risks has a named mitigation owner with a dated mitigation action. | C5: Register columns Owner + Mitigation-date populated. | D5: Completed register. | E5: Any blank → Correction. | F5: DHDD Director | G5: Pending
A6: K03 | B6: EHSSP funding-cliff mitigation is concrete (named funder, amount, date) — not just ‘W1-11’. | C6: Inspect W1-11 plan. | D6: Concrete bridge plan. | E6: Generic W1-11 reference → Correction. | F6: RDIP PM | G6: Pending
A7: K04 | B7: DHDD recruitment-failure mitigation is credible (named salary bands, secondments, or RDIP supplementation). | C7: Check mitigation statement. | D7: Recruitment mitigation plan. | E7: “Competitive salaries” with no numbers → Clarification. | F7: DHDD Director + PSC | G7: Pending
A8: K05 | B8: RDIP G-Cloud delay risk has a concrete contingency (extended interim hosting, budget top-up). | C8: Inspect contingency. | D8: Contingency plan. | E8: “Extend interim” without budget → Clarification. | F8: RDIP PM | G8: Pending
A9: K06 | B9: eCRVS API unavailability has a Plan B (e.g. flat-file nightly, manual verification). | C9: Check Plan B. | D9: Plan-B doc. | E9: Plan B absent → Correction. | F9: DHDD Director + eCRVS lead | G9: Pending
A10: K07 | B10: NIN production suspension has a probabilistic-matching fallback with acceptable thresholds. | C10: Check fallback. | D10: Matching-threshold SOP. | E10: No fallback thresholds → Clarification. | F10: DHDD Director | G10: Pending
A11: K08 | B11: DPA absence has an interim legal instrument (SI, Ministerial Order) covering health-data exchange. | C11: Check instrument draft. | D11: Interim instrument. | E11: Nothing drafted → Objection-risk. | F11: DPO + MoH PS | G11: Pending
A12: K09 | B12: EHR clinician-adoption risk has a change-management plan with named champions per pilot facility. | C12: Check OCM plan. | D12: OCM plan + champions list. | E12: Generic OCM → Correction. | F12: Director of Health Services | G12: Pending
A13: K10 | B13: Government budget-line commitment has a concrete political mechanism (MoF instruction, budget-circular line). | C13: Inspect mechanism. | D13: Mechanism doc. | E13: Generic aspiration → Objection-risk. | F13: MoH PS + MoF | G13: Pending
A14: K11 | B14: Residual risks after mitigation are truly residual (not just transferred to another line). | C14: Inspect before/after severity. | D14: Residual-risk note. | E14: Transfers disguised as mitigations → Correction. | F14: DHDD Director | G14: Pending
A15: K12 | B15: Risk-review cadence is established (quarterly register refresh; monthly Critical review). | C15: Calendar commitments. | D15: Cadence note. | E15: No cadence → Clarification. | F15: DHDD Director | G15: Pending

Sheet S Coverage
A1: S — Stakeholder Coverage Tracking
A3: ID | B3: Check / Statement | C3: How to Verify (Procedure / Probe) | D3: Evidence Required | E3: Red-flag Pattern | F3: Owner | G3: Status | H3: Notes
A4: S01 | B4: Every core-validation item has a primary response owner who is physically in the room (or on named proxy). | C4: For each item (B/D/A/I/T/R1/R2/R3/R4) verify owner is present. | D4: Attendance register annotated per item. | E4: Owner absent without proxy → item deferred; re-run post-workshop. | F4: ITU Project Manager | G4: Pending
A5: S02 | B5: Every OBJECTION has a documented alternative position from the objector. | C5: Walk objections; missing alternative → chase. | D5: Feedback log alternative column. | E5: Bare objection (no alternative) → escalate. | F5: ITU Analyst | G5: Pending
A6: S03 | B6: Every CORRECTION has proposed alternative text from the corrector. | C6: Walk corrections; missing text → chase. | D6: Feedback log proposed-change column. | E6: Bare correction (no text) → escalate. | F6: ITU Analyst | G6: Pending
A7: S04 | B7: Every CLARIFICATION has a written answer (either in session or in the written-response log). | C7: Walk clarifications; unanswered → assign to Lead Architect 48h. | D7: Clarification answer log. | E7: Unanswered after 48h → escalate. | F7: ITU Project Manager | G7: Pending
A8: S05 | B8: Every ENHANCEMENT has a decision (adopt / defer to backlog / decline with reason). | C8: Walk enhancements; undecided → decide. | D8: Enhancement decision log. | E8: “Will consider” → re-classify as deferred or declined with reason. | F8: DHDD Director | G8: Pending

Sheet PR Process
A1: PR — Process-Integrity Self-Check (close-out)
A3: ID | B3: Check / Statement | C3: How to Verify (Procedure / Probe) | D3: Evidence Required | E3: Red-flag Pattern | F3: Owner | G3: Status | H3: Notes
A4: PR01 | B4: Every Day-1 session ended with all planned classifications logged. | C4: Count scheduled items vs logged classifications. | D4: Day-1 log tally. | E4: Missing classifications → reopen Day 2 morning. | F4: ITU Analyst | G4: Pending
A5: PR02 | B5: Every Day-2 session ended with all planned classifications logged. | C5: As above. | D5: Day-2 log tally. | E5: Missing → reopen Day 3 morning. | F5: ITU Analyst | G5: Pending
A6: PR03 | B6: Every Day-3 session ended with all planned classifications logged. | C6: As above. | D6: Day-3 log tally. | E6: Missing → escalate to written response. | F6: ITU Analyst | G6: Pending
A7: PR04 | B7: Parking-lot has zero open items at end of Day 3 (or each open item has a written-response owner named). | C7: Parking-lot review in S3.5. | D7: Parking-lot close-out sheet. | E7: Open item with no owner → PM assigns. | F7: ITU Project Manager | G7: Pending
A8: PR05 | B8: Decision memo signed by PS, PDGA DG, RDIP PM before adjournment. | C8: Printed memo signed. | D8: Scanned signed memo in PMU file. | E8: Missing signature → workshop not formally closed. | F8: ITU Project Manager | G8: Pending
A9: PR06 | B9: Feedback log e-mailed to all participants within 24h. | C9: Distribution tracker. | D9: Sent-e-mail log. | E9: Missed 24h → remedial send + apology. | F9: ITU Analyst | G9: Pending

Sheet Dashboard
A1: Validation Progress Dashboard
A3: Core validation tabs (classification column J)
A5: Tab | B5: Total | C5: Confirmed | D5: Correction | E5: Clarification | F5: Enhancement | G5: Objection | H5: N/A | I5: Pending | J5: % Closed
A6: B Business | B6: 7 | C6: =COUNTIF('B Business'!J4:J10,"Confirmed OK") -> 0 | D6: =COUNTIF('B Business'!J4:J10,"Correction") -> 0 | E6: =COUNTIF('B Business'!J4:J10,"Clarification") -> 0 | F6: =COUNTIF('B Business'!J4:J10,"Enhancement") -> 0 | G6: =COUNTIF('B Business'!J4:J10,"Objection") -> 0 | H6: =COUNTIF('B Business'!J4:J10,"N/A") -> 0 | I6: =COUNTIF('B Business'!J4:J10,"Pending") -> 7 | J6: =IF(B6=0,0,(B6-I6)/B6) -> 0
A7: D Data | B7: 6 | C7: =COUNTIF('D Data'!J4:J9,"Confirmed OK") -> 0 | D7: =COUNTIF('D Data'!J4:J9,"Correction") -> 0 | E7: =COUNTIF('D Data'!J4:J9,"Clarification") -> 0 | F7: =COUNTIF('D Data'!J4:J9,"Enhancement") -> 0 | G7: =COUNTIF('D Data'!J4:J9,"Objection") -> 0 | H7: =COUNTIF('D Data'!J4:J9,"N/A") -> 0 | I7: =COUNTIF('D Data'!J4:J9,"Pending") -> 6 | J7: =IF(B7=0,0,(B7-I7)/B7) -> 0
A8: A Application | B8: 8 | C8: =COUNTIF('A Application'!J4:J11,"Confirmed OK") -> 0 | D8: =COUNTIF('A Application'!J4:J11,"Correction") -> 0 | E8: =COUNTIF('A Application'!J4:J11,"Clarification") -> 0 | F8: =COUNTIF('A Application'!J4:J11,"Enhancement") -> 0 | G8: =COUNTIF('A Application'!J4:J11,"Objection") -> 0 | H8: =COUNTIF('A Application'!J4:J11,"N/A") -> 0 | I8: =COUNTIF('A Application'!J4:J11,"Pending") -> 8 | J8: =IF(B8=0,0,(B8-I8)/B8) -> 0
A9: I Integration | B9: 5 | C9: =COUNTIF('I Integration'!J4:J8,"Confirmed OK") -> 0 | D9: =COUNTIF('I Integration'!J4:J8,"Correction") -> 0 | E9: =COUNTIF('I Integration'!J4:J8,"Clarification") -> 0 | F9: =COUNTIF('I Integration'!J4:J8,"Enhancement") -> 0 | G9: =COUNTIF('I Integration'!J4:J8,"Objection") -> 0 | H9: =COUNTIF('I Integration'!J4:J8,"N/A") -> 0 | I9: =COUNTIF('I Integration'!J4:J8,"Pending") -> 5 | J9: =IF(B9=0,0,(B9-I9)/B9) -> 0
A10: T Technology | B10: 6 | C10: =COUNTIF('T Technology'!J4:J9,"Confirmed OK") -> 0 | D10: =COUNTIF('T Technology'!J4:J9,"Correction") -> 0 | E10: =COUNTIF('T Technology'!J4:J9,"Clarification") -> 0 | F10: =COUNTIF('T Technology'!J4:J9,"Enhancement") -> 0 | G10: =COUNTIF('T Technology'!J4:J9,"Objection") -> 0 | H10: =COUNTIF('T Technology'!J4:J9,"N/A") -> 0 | I10: =COUNTIF('T Technology'!J4:J9,"Pending") -> 6 | J10: =IF(B10=0,0,(B10-I10)/B10) -> 0
A11: R1 Timeline | B11: 7 | C11: =COUNTIF('R1 Timeline'!J4:J10,"Confirmed OK") -> 0 | D11: =COUNTIF('R1 Timeline'!J4:J10,"Correction") -> 0 | E11: =COUNTIF('R1 Timeline'!J4:J10,"Clarification") -> 0 | F11: =COUNTIF('R1 Timeline'!J4:J10,"Enhancement") -> 0 | G11: =COUNTIF('R1 Timeline'!J4:J10,"Objection") -> 0 | H11: =COUNTIF('R1 Timeline'!J4:J10,"N/A") -> 0 | I11: =COUNTIF('R1 Timeline'!J4:J10,"Pending") -> 7 | J11: =IF(B11=0,0,(B11-I11)/B11) -> 0
A12: R2 Investment | B12: 5 | C12: =COUNTIF('R2 Investment'!J4:J8,"Confirmed OK") -> 0 | D12: =COUNTIF('R2 Investment'!J4:J8,"Correction") -> 0 | E12: =COUNTIF('R2 Investment'!J4:J8,"Clarification") -> 0 | F12: =COUNTIF('R2 Investment'!J4:J8,"Enhancement") -> 0 | G12: =COUNTIF('R2 Investment'!J4:J8,"Objection") -> 0 | H12: =COUNTIF('R2 Investment'!J4:J8,"N/A") -> 0 | I12: =COUNTIF('R2 Investment'!J4:J8,"Pending") -> 5 | J12: =IF(B12=0,0,(B12-I12)/B12) -> 0
A13: R3 Risks | B13: 3 | C13: =COUNTIF('R3 Risks'!J4:J6,"Confirmed OK") -> 0 | D13: =COUNTIF('R3 Risks'!J4:J6,"Correction") -> 0 | E13: =COUNTIF('R3 Risks'!J4:J6,"Clarification") -> 0 | F13: =COUNTIF('R3 Risks'!J4:J6,"Enhancement") -> 0 | G13: =COUNTIF('R3 Risks'!J4:J6,"Objection") -> 0 | H13: =COUNTIF('R3 Risks'!J4:J6,"N/A") -> 0 | I13: =COUNTIF('R3 Risks'!J4:J6,"Pending") -> 3 | J13: =IF(B13=0,0,(B13-I13)/B13) -> 0
A14: R4 Governance | B14: 5 | C14: =COUNTIF('R4 Governance'!J4:J8,"Confirmed OK") -> 0 | D14: =COUNTIF('R4 Governance'!J4:J8,"Correction") -> 0 | E14: =COUNTIF('R4 Governance'!J4:J8,"Clarification") -> 0 | F14: =COUNTIF('R4 Governance'!J4:J8,"Enhancement") -> 0 | G14: =COUNTIF('R4 Governance'!J4:J8,"Objection") -> 0 | H14: =COUNTIF('R4 Governance'!J4:J8,"N/A") -> 0 | I14: =COUNTIF('R4 Governance'!J4:J8,"Pending") -> 5 | J14: =IF(B14=0,0,(B14-I14)/B14) -> 0
A15: CORE TOTAL | B15: =SUM(B6:B14) -> 52 | C15: =SUM(C6:C14) -> 0 | D15: =SUM(D6:D14) -> 0 | E15: =SUM(E6:E14) -> 0 | F15: =SUM(F6:F14) -> 0 | G15: =SUM(G6:G14) -> 0 | H15: =SUM(H6:H14) -> 0 | I15: =SUM(I6:I14) -> 52 | J15: =IF(B15=0,0,(B15-I15)/B15) -> 0
A17: Supplementary tabs (status column G)
A19: Tab | B19: Total | C19: Done | D19: In progress | E19: Pending | F19: Blocked | G19: Failed | H19: N/A | I19: % Done
A20: V0 Pre-workshop | B20: 15 | C20: =COUNTIF('V0 Pre-workshop'!G4:G18,"Done") -> 0 | D20: =COUNTIF('V0 Pre-workshop'!G4:G18,"In progress") -> 0 | E20: =COUNTIF('V0 Pre-workshop'!G4:G18,"Pending") -> 15 | F20: =COUNTIF('V0 Pre-workshop'!G4:G18,"Blocked") -> 0 | G20: =COUNTIF('V0 Pre-workshop'!G4:G18,"Failed") -> 0 | H20: =COUNTIF('V0 Pre-workshop'!G4:G18,"N/A") -> 0 | I20: =IF(B20=0,0,C20/B20) -> 0
A21: P Premise | B21: 8 | C21: =COUNTIF('P Premise'!G4:G11,"Done") -> 0 | D21: =COUNTIF('P Premise'!G4:G11,"In progress") -> 0 | E21: =COUNTIF('P Premise'!G4:G11,"Pending") -> 8 | F21: =COUNTIF('P Premise'!G4:G11,"Blocked") -> 0 | G21: =COUNTIF('P Premise'!G4:G11,"Failed") -> 0 | H21: =COUNTIF('P Premise'!G4:G11,"N/A") -> 0 | I21: =IF(B21=0,0,C21/B21) -> 0
A22: G Commitments | B22: 10 | C22: =COUNTIF('G Commitments'!G4:G13,"Done") -> 0 | D22: =COUNTIF('G Commitments'!G4:G13,"In progress") -> 0 | E22: =COUNTIF('G Commitments'!G4:G13,"Pending") -> 10 | F22: =COUNTIF('G Commitments'!G4:G13,"Blocked") -> 0 | G22: =COUNTIF('G Commitments'!G4:G13,"Failed") -> 0 | H22: =COUNTIF('G Commitments'!G4:G13,"N/A") -> 0 | I22: =IF(B22=0,0,C22/B22) -> 0
A23: L Legal | B23: 6 | C23: =COUNTIF('L Legal'!G4:G9,"Done") -> 0 | D23: =COUNTIF('L Legal'!G4:G9,"In progress") -> 0 | E23: =COUNTIF('L Legal'!G4:G9,"Pending") -> 6 | F23: =COUNTIF('L Legal'!G4:G9,"Blocked") -> 0 | G23: =COUNTIF('L Legal'!G4:G9,"Failed") -> 0 | H23: =COUNTIF('L Legal'!G4:G9,"N/A") -> 0 | I23: =IF(B23=0,0,C23/B23) -> 0
A24: X Cross-ref | B24: 10 | C24: =COUNTIF('X Cross-ref'!G4:G13,"Done") -> 0 | D24: =COUNTIF('X Cross-ref'!G4:G13,"In progress") -> 0 | E24: =COUNTIF('X Cross-ref'!G4:G13,"Pending") -> 10 | F24: =COUNTIF('X Cross-ref'!G4:G13,"Blocked") -> 0 | G24: =COUNTIF('X Cross-ref'!G4:G13,"Failed") -> 0 | H24: =COUNTIF('X Cross-ref'!G4:G13,"N/A") -> 0 | I24: =IF(B24=0,0,C24/B24) -> 0
A25: K Risks | B25: 12 | C25: =COUNTIF('K Risks'!G4:G15,"Done") -> 0 | D25: =COUNTIF('K Risks'!G4:G15,"In progress") -> 0 | E25: =COUNTIF('K Risks'!G4:G15,"Pending") -> 12 | F25: =COUNTIF('K Risks'!G4:G15,"Blocked") -> 0 | G25: =COUNTIF('K Risks'!G4:G15,"Failed") -> 0 | H25: =COUNTIF('K Risks'!G4:G15,"N/A") -> 0 | I25: =IF(B25=0,0,C25/B25) -> 0
A26: S Coverage | B26: 5 | C26: =COUNTIF('S Coverage'!G4:G8,"Done") -> 0 | D26: =COUNTIF('S Coverage'!G4:G8,"In progress") -> 0 | E26: =COUNTIF('S Coverage'!G4:G8,"Pending") -> 5 | F26: =COUNTIF('S Coverage'!G4:G8,"Blocked") -> 0 | G26: =COUNTIF('S Coverage'!G4:G8,"Failed") -> 0 | H26: =COUNTIF('S Coverage'!G4:G8,"N/A") -> 0 | I26: =IF(B26=0,0,C26/B26) -> 0
A27: PR Process | B27: 6 | C27: =COUNTIF('PR Process'!G4:G9,"Done") -> 0 | D27: =COUNTIF('PR Process'!G4:G9,"In progress") -> 0 | E27: =COUNTIF('PR Process'!G4:G9,"Pending") -> 6 | F27: =COUNTIF('PR Process'!G4:G9,"Blocked") -> 0 | G27: =COUNTIF('PR Process'!G4:G9,"Failed") -> 0 | H27: =COUNTIF('PR Process'!G4:G9,"N/A") -> 0 | I27: =IF(B27=0,0,C27/B27) -> 0
A28: SUPP TOTAL | B28: =SUM(B20:B27) -> 72 | C28: =SUM(C20:C27) -> 0 | D28: =SUM(D20:D27) -> 0 | E28: =SUM(E20:E27) -> 72 | F28: =SUM(F20:F27) -> 0 | G28: =SUM(G20:G27) -> 0 | H28: =SUM(H20:H27) -> 0 | I28: =IF(B28=0,0,C28/B28) -> 0
A31: Exit gate for workshop close
A32: Gate 1 | B32: All core items classified (0 Pending) | C32: =IF(I15=0,"PASS","FAIL") -> FAIL
A33: Gate 2 | B33: All supplementary items Done or N/A (no Pending/Blocked/Failed) | C33: =IF(E28+F28+G28=0,"PASS","FAIL") -> FAIL
A34: Gate 3 | B34: Every Objection has disposition (S Coverage S02 Done) | C34: MANUAL VERIFY — see S Coverage tab
A35: Gate 4 | B35: Decision memo signed (PR05 Done) | C35: MANUAL VERIFY — see PR Process tab
A36: Gate 5 | B36: Feedback log distributed (PR06 Done) | C36: MANUAL VERIFY — see PR Process tab
